nalangTest/test1.py
nalangTest/test2.py
my_first_upload_test-0.0.0.2.dist-info/METADATA
my_first_upload_test-0.0.0.2.dist-info/WHEEL
my_first_upload_test-0.0.0.2.dist-info/top_level.txt
my_first_upload_test-0.0.0.2.dist-info/RECORD
