Metadata-Version: 2.1
Name: my-first-upload-test
Version: 0.0.0.2
Summary: My First Test Package
Home-page: https://www.naver.com
Author: far_away
Author-email: atker14@gmail.com
License: MIT
Platform: UNKNOWN
Requires-Python: >=3
